README.md
setup.cfg
setup.py
gen_validate.egg-info/PKG-INFO
gen_validate.egg-info/SOURCES.txt
gen_validate.egg-info/dependency_links.txt
gen_validate.egg-info/requires.txt
gen_validate.egg-info/top_level.txt
validate/__init__.py
validate/validate_pb2.py
validate/validate_pb2_grpc.py